alliance/__init__.py
alliance/asgi.py
alliance/settings.py
alliance/urls.py
alliance/wsgi.py
artd_alliance/__init__.py
artd_alliance/admin.py
artd_alliance/apps.py
artd_alliance/context_processors.py
artd_alliance/models.py
artd_alliance/signals.py
artd_alliance/tests.py
artd_alliance/views.py
artd_alliance/migrations/0001_initial.py
artd_alliance/migrations/0002_alliance_comments_and_more.py
artd_alliance/migrations/0003_alter_alliance_comments_alliancecommentchange.py
artd_alliance/migrations/0004_alter_alliancecommentchange_options.py
artd_alliance/migrations/0005_alter_alliance_benefit_type.py
artd_alliance/migrations/0006_alliance_coupon_length_alliance_coupon_prefix_and_more.py
artd_alliance/migrations/0007_remove_alliance_coupon_length_and_more.py
artd_alliance/migrations/0008_alter_alliance_coupon_prefix_and_more.py
artd_alliance/migrations/0009_alliance_end_at_alliance_is_permanent_and_more.py
artd_alliance/migrations/0010_alliance_value.py
artd_alliance/migrations/0011_alter_alliance_code_alliance.py
artd_alliance/migrations/0012_alter_alliance_end_at_alter_alliance_start_at.py
artd_alliance/migrations/0013_alliance_coupons.py
artd_alliance/migrations/0014_alliance_uses_per_coupon_and_more.py
artd_alliance/migrations/0015_alter_alliance_coupon_quantity_and_more.py
artd_alliance/migrations/0016_remove_alliance_generate_coupons.py
artd_alliance/migrations/0017_alter_ally_address_alter_ally_email_alter_ally_logo.py
artd_alliance/migrations/__init__.py
artd_alliance-1.0.7.dist-info/LICENSE
artd_alliance-1.0.7.dist-info/METADATA
artd_alliance-1.0.7.dist-info/WHEEL
artd_alliance-1.0.7.dist-info/top_level.txt
artd_alliance-1.0.7.dist-info/RECORD
